waterq.py
waterq-0.0.1.dist-info/METADATA
waterq-0.0.1.dist-info/WHEEL
waterq-0.0.1.dist-info/entry_points.txt
waterq-0.0.1.dist-info/top_level.txt
waterq-0.0.1.dist-info/RECORD
