Metadata-Version: 2.1
Name: waterq
Version: 0.0.1
Summary: waterq for detecting water quality anomalities
Home-page: https://github.com/y-takefuji/water
Author: yoshiyasu takefuji
Author-email: takefuji@keio.jp
Project-URL: Bug Tracker, https://github.com/y-takefuji/water
Classifier: Programming Language :: Python :: 3
Classifier: License :: OSI Approved :: MIT License
Classifier: Operating System :: OS Independent
Requires-Python: >=3.8
